{"data_non_statistical":false,"goal_meta_link":"https://unstats.un.org/sdgs/metadata/files/Metadata-10-04-01.pdf","goal_meta_link_text":"United Nations Sustainable Development Goals Metadata (PDF 190 KB)","graph_title":"Proporci\u00f3n del PIB generada por el trabajo","graph_type":"line","indicator_number":"10.4.2","indicator_definition":"global_indicators.10-4-2-indicator_definition","indicator_name":"Efecto redistributivo de la pol\u00edtica fiscal","indicator_sort_order":"10-04-02","published":true,"reporting_status":"notstarted","sdg_goal":"10","target_name":"Adoptar poli\u0301ticas, especialmente fiscales, salariales y de proteccio\u0301n social, y lograr progresivamente una mayor igualdad","target_id":"10.4","un_custodian_agency":"International Labour Organization (ILO)","un_designated_tier":"2","source_active_1":true,"source_organisation_1":"Instituto Canario de Estad\u00edstica (ISTAC)","source_url_1":"http://www.gobiernodecanarias.org/istac/","source_url_text_1":"ISTAC","computation_units":null,"prev_indicator":null,"next_indicator":null,"page_content":"","indicator":"10.4.2"}